CHANGES
MANIFEST.in
Makefile
README
setup.cfg
setup.py
twinstance
test/__init__.py
test/__init__.pyc
test/fixtures.py
test/fixtures.pyc
test/index.html
test/test_manage.py
test/test_serialize_binary.py
test/test_serialize_tiddler.py
test/test_web_friendlywiki.py
test/test_web_tiddlywiki_title.py
test/__pycache__/test_manage.cpython-27-PYTEST.pyc
test/__pycache__/test_serialize_binary.cpython-27-PYTEST.pyc
test/__pycache__/test_serialize_tiddler.cpython-27-PYTEST.pyc
test/__pycache__/test_web_friendlywiki.cpython-27-PYTEST.pyc
test/__pycache__/test_web_tiddlywiki_title.cpython-27-PYTEST.pyc
test/data/index.html
test/data/peermore.png
test/data/wiki.html
test/data/zero.bin
tiddlywebwiki/__init__.py
tiddlywebwiki/config.py
tiddlywebwiki/instance.py
tiddlywebwiki/serialization.py
tiddlywebwiki.egg-info/PKG-INFO
tiddlywebwiki.egg-info/SOURCES.txt
tiddlywebwiki.egg-info/dependency_links.txt
tiddlywebwiki.egg-info/not-zip-safe
tiddlywebwiki.egg-info/requires.txt
tiddlywebwiki.egg-info/top_level.txt
tiddlywebwiki/resources/empty.html
tiddlywebwiki/resources/store/bags/system/description
tiddlywebwiki/resources/store/bags/system/policy
tiddlywebwiki/resources/store/bags/system/tiddlers/BinaryTiddlersPlugin/1
tiddlywebwiki/resources/store/bags/system/tiddlers/DiffFormatter/1
tiddlywebwiki/resources/store/bags/system/tiddlers/RevisionsCommandPlugin/1
tiddlywebwiki/resources/store/bags/system/tiddlers/ServerSideSavingPlugin/1
tiddlywebwiki/resources/store/bags/system/tiddlers/TiddlyWebAdaptor/1
tiddlywebwiki/resources/store/bags/system/tiddlers/TiddlyWebConfig/1
wikklytext/__init__.py
wikklytext/base.py
wikklytext/buildHTML.py
wikklytext/buildXML.py
wikklytext/cache.py
wikklytext/cmdline.py
wikklytext/coremacros.py
wikklytext/error.py
wikklytext/eval.py
wikklytext/lexer.py
wikklytext/macro.py
wikklytext/parser.py
wikklytext/plugapi.py
wikklytext/plugins.py
wikklytext/port.py
wikklytext/serialize.py
wikklytext/t.py
wikklytext/util.py
wikklytext/version.py
wikklytext/wikwords.py
wikklytext/xmlvalid.py
wikklytext/scripts/__init__.py
wikklytext/scripts/twextract.py
wikklytext/scripts/wik.py
wikklytext/scripts/wikboot.py
wikklytext/scripts/wikgui.py
wikklytext/scripts/wikkly2html.py
