Metadata-Version: 1.0
Name: tiddlywebwiki
Version: 0.69.0
Summary: A TiddlyWeb plugin to provide a multi-user TiddlyWiki environment.
Home-page: UNKNOWN
Author: FND
Author-email: FNDo@gmx.net
License: UNKNOWN
Platform: Posix; MacOS X; Windows
